Workbook

Sheet Instrucciones
B2: Plantilla de Importacion de Vehiculos UE -> Espania
B3: Herramienta reutilizable para calcular coste real, margen y checklist de cualquier importacion futura.
B5: Como usar esta plantilla
B6: 1. Rellena 'Vehiculo y resumen' con la info del anuncio (celdas azules) y con los hallazgos de la investigacion del modelo (relleno amarillo: fiabilidad, recalls, precio de mercado real). El Resumen ejecutivo se calcula solo.
B7: 2. La pestania 'Numeros' calcula el coste total puesto en Espania, el margen de reventa y guarda los comparables de mercado - todo en una sola hoja.
B8: 3. Usa 'Checklist inspeccion' durante la visita al vehiculo (incluye prioridad Critico/Importante/Menor), y 'Checklist documentacion' antes de firmar y tras la llegada (incluye los plazos legales de matriculacion).
B9: 4. 'Cronograma logistico' es tu plantilla de viaje completa: ida, protocolo financiero, dia del cierre, plan de contingencia, registro de riesgos y vuelta.
B10: 5. 'Contactos clave' es ficha de apoyo rapido, reutilizable en cualquier operacion.
B11: 6. 'Plantillas de mensaje' cubre todo el ciclo (contacto, negociacion, cierre, seguimiento, reventa) en espaniol, ingles y aleman, en tono profesional (email) y distendido (WhatsApp). Copia la fila que necesites y sustituye los campos [ENTRE CORCHETES].
B12: 7. El registro historico de rentabilidad entre operaciones vive en un archivo aparte (Registro_Operaciones_Importacion.xlsx), no en esta plantilla.
B14: Codigo de colores
B15: Texto AZUL = celda de entrada (rellena tu los datos)
... B24: - La seccion 'Investigacion del modelo' recoge hallazgos de busqueda web (manual o automatizada); son orientativos y deben contrastarse con la unidad real durante la inspeccion.

Sheet Vehiculo y resumen
A1: Vehiculo y resumen
A2: Rellena los datos del anuncio (celdas azules). El bloque de investigacion se rellena con la busqueda del skill. El resumen de abajo se actualiza solo.
A4: DATOS DEL VEHICULO (del anuncio)
A5: Campo | B5: Valor | C5: Notas / fuente
A6: Marca y modelo | B6: Volkswagen Golf VII Lim. R-Line | C6: Rellenar segun anuncio
A7: Motorizacion | B7: 1.0 TSI DSG (85 kW / 116 CV)
A8: Combustible | B8: Gasolina
A9: Cambio | B9: Automatico (DSG)
A10: Traccion | B10: Delantera
A11: Puertas / plazas | B11: 5 puertas / 5 plazas
A12: Anio / 1a matriculacion | B12: 05/2019
A13: Kilometraje | B13: 137600 | C13: km
A14: No de propietarios | B14: 2
A15: Color exterior
A16: Color / tapiceria interior
A17: Equipamiento destacado | B17: Panorama-Schiebedach electrico, Climatronic 2 zonas, Business-Paket, camara trasera, App-Connect | C17: Copiar del anuncio
A18: Precio anuncio (con IVA origen) | B18: 12990 | C18: EUR, precio final del anuncio
A19: CO2 homologado (g/km NEDC) | B19: 109 | C19: Confirmar con el COC real antes de comprometerse
A20: Garantia ofrecida por el vendedor | C20: Meses / cobertura si aplica
A21: Accidentes declarados | B21: No declara accidentes (a confirmar) | C21: Segun el anuncio; verificar en inspeccion
A22: Historial de mantenimiento disponible | B22: Si (parcial) | C22: Si / No / Parcial
A23: Vendedor: tipo | B23: Profesional / concesionario | C23: Profesional / Particular (afecta a fiscalidad)
A24: Vendedor: nombre y ubicacion | B24: AlpenDrive, Bad Endorf (DE)
A25: URL del anuncio | C25: Pegar enlace
A26: Enlace a fotos / galeria adicional
A27: Persona de contacto | B27: Martin
A28: Fecha de la captura del anuncio | B28: 15/07/2026 | C28: Para saber si el anuncio sigue vigente
A30: INVESTIGACION DEL MODELO (busqueda web)
A31: Relleno amarillo = hallazgo de investigacion a confirmar. Rellenado por el proceso de investigacion (manual o skill) antes de dar el visto bueno a la operacion.
A32: Aspecto | B32: Hallazgo | C32: Fuente / URL
A33: Problemas / averias comunes conocidos de este motor y modelo
A34: Campanias de recall oficiales pendientes para este modelo (y VIN si es identificable)
A35: Rango de precio de mercado real encontrado (contrastar con 'Numeros' > Comparables)
A36: Fiabilidad general / opinion media de propietarios y prensa especializada
A37: Otros datos relevantes de esta unidad concreta (garantia de fabrica restante, campanias previas aplicadas, etc.)
A39: RESUMEN EJECUTIVO
A40: Vista rapida de la operacion actual, calculada a partir de 'Numeros' y los checklists.
A42: COSTE, HONORARIOS Y PRECIO AL CLIENTE
A43: Coste total puesto en Espania (minimo) | B43: =Numeros!B24
A44: Coste total puesto en Espania (maximo) | B44: =Numeros!C24
A45: Precio todo incluido al cliente (escenario coste minimo) | B45: =Numeros!B34
A46: Precio todo incluido al cliente (escenario coste maximo) | B46: =Numeros!B35
A47: Honorarios de servicio | B47: =Numeros!B32
A48: Honorarios (%) sobre coste total minimo | B48: =Numeros!B36
A49: Precio medio de comparables de mercado | B49: =Numeros!G52
A51: PROGRESO DE REVISION
A52: Checklist inspeccion - puntos OK | B52: =COUNTIF('Checklist inspeccion'!C:C,"OK")
A53: Checklist inspeccion - puntos a revisar | B53: =COUNTIF('Checklist inspeccion'!C:C,"Revisar")
A54: Checklist inspeccion - total de puntos | B54: =COUNT('Checklist inspeccion'!A:A)
A55: Documentacion - recibidos | B55: =COUNTIF('Checklist documentacion'!C6:C20,"Si")
A56: Documentacion - total requerida | B56: =COUNTA('Checklist documentacion'!B6:B20)
A58: Nota: si "puntos a revisar" es mayor que 0, hay algo detectado en la inspeccion que requiere decision antes de firmar.

Sheet Numeros
A1: Numeros - Presupuesto, honorarios y comparables
A2: Coste total puesto en Espania, honorarios de servicio y comparables de mercado. Celdas azules ajustables; el resto se recalcula solo.
A4: PRESUPUESTO DE IMPORTACION
A5: Concepto | B5: Minimo (EUR) | C5: Maximo (EUR) | D5: Notas
A6: Precio de compra | B6: ='Vehiculo y resumen'!B18 | C6: ='Vehiculo y resumen'!B18 | D6: Enlazado a 'Vehiculo y resumen'. Incluye IVA de origen si aplica.
A7: Vuelo / tren / bus (ida) | B7: 120 | C7: 180
A8: Gasolina de vuelta | B8: 150 | C8: 220
A9: Peajes | B9: 90 | C9: 110
A10: Vinietas / tasas tunel | B10: 10 | C10: 20
A11: Placas provisionales + seguro temporal | B11: 150 | C11: 200
A12: Alojamiento y manutencion | B12: 100 | C12: 200
A13: Subtotal logistica de viaje | B13: =SUM(B7:B12) | C13: =SUM(C7:C12)
A15: ITV espaniola de importacion | B15: 100 | C15: 150
A16: IEDMT (impuesto de matriculacion) | B16: =IF('Vehiculo y resumen'!B19<=120,0,IF('Vehiculo y resumen'!B19<=160,'Vehiculo y resumen'!B18*0.0475,IF('Vehiculo y resumen'!B19<=200,'Vehiculo y resumen'!B18*0.0975,'Vehiculo y resumen'!B18*0.1475))) | C16: =IF('Vehiculo y resumen'!B19<=120,0,IF('Vehiculo y resumen'!B19<=160,'Vehiculo y resumen'!B18*0.0475,IF('Vehiculo y resumen'!B19<=200,'Vehiculo y resumen'!B18*0.0975,'Vehiculo y resumen'!B18*0.1475))) | D16: Tramos CO2 orientativos: 0% <=120g/km, 4.75% 121-160, 9.75% 161-200, 14.75% >200. Verificar tabla vigente.
A17: Tasa DGT matriculacion | B17: 55 | C17: 55
A18: Gestoria (0 si lo tramitas tu mismo) | B18: 0 | C18: 400
A19: Placas nuevas Espania | B19: 20 | C19: 20
A20: Subtotal impuestos y tramites Espania | B20: =SUM(B15:B19) | C20: =SUM(C15:C19)
A22: Coste financiacion / intereses prestamo (si aplica) | B22: 0 | C22: 700 | D22: Puente y devuelto rapido = coste bajo. Prestamo largo a tipo alto (10-12%) = coste alto. Negociar tipo en oficina, no por la app.
A24: COSTE TOTAL PUESTO EN ESPANIA | B24: =B6+B13+B20+B22 | C24: =C6+C13+C20+C22
A27: HONORARIOS Y PRECIO TODO INCLUIDO AL CLIENTE
A28: Concepto | B28: Valor (EUR) | C28: Notas
A29: Coste total puesto en Espania (minimo) | B29: =B24
A30: Coste total puesto en Espania (maximo) | B30: =C24
A32: Honorarios de servicio (tramo: hasta 15.000E=1.500E / 15.000-30.000E=2.000-2.500E / +30.000E=2.500-3.500E) | B32: 1500 | C32: Ajustar segun comparables reales de mercado (ver bloque de abajo)
A34: Precio todo incluido al cliente (escenario coste minimo) | B34: =B29+B32
A35: Precio todo incluido al cliente (escenario coste maximo) | B35: =B30+B32
A36: Honorarios (%) sobre coste total, escenario minimo | B36: =B32/B29
A39: COMPARABLES DE MERCADO
A40: Registra aqui anuncios similares que encuentres (o que investigue el skill) para defender tu precio de compra y de venta con datos reales.
A41: Portal | B41: URL | C41: Motor | D41: CV | E41: Anio | F41: Km | G41: Precio (EUR) | H41: Ubicacion | I41: Notas
A42: Flexicar | C42: 1.5 TSI DSG Variant | D42: 150 | E42: 2019 | F42: 73541 | G42: 20490 | H42: Barcelona | I42: Variant (familiar), no comparable directo: carroceria distinta a la del hatchback
A43: Flexicar | C43: 1.5 TSI DSG | D43: 150 | E43: 2018 | F43: 104000 | G43: 16490 | H43: Barcelona (Sant Just) | I43: Hatchback R-Line, SIN techo panoramico. El R-Line mas barato encontrado en Flexicar
A44: Referencia generica | C44: 1.5 TSI DSG | D44: 150 | E44: 2018-2019 | G44: 17000 | H44: Espania (varios) | I44: Precio orientativo de mercado para R-Line bien equipado, citado como referencia
A52: Precio medio de comparables | G52: =IFERROR(AVERAGE(G42:G50),0)
A54: Nota: compara con al menos 3-5 anuncios similares (mismo motor, anio y kilometraje) para defender el precio de compra y verificar que el precio todo incluido queda por debajo o en linea con el mercado espaniol (semaforo).
A56: Comparativa rapida (grafico)
A57: Coste total (minimo) | B57: =B24
A58: Precio de venta estimado | B58: =B32
A59: Precio medio de comparables | B59: =G52

Sheet Checklist inspeccion
A1: Checklist de inspeccion fisica del vehiculo
A2: Usar durante la visita presencial, punto por punto, antes de firmar nada. Prioridad orienta que hallazgos son bloqueantes.
A4: # | B4: Punto a revisar | C4: Prioridad | D4: Estado | E4: Notas / evidencia
B5: EXTERIOR
A6: 1 | B6: Faros delanteros: sin condensacion, sin grietas, buen funcionamiento de luces de cruce/carretera | C6: Importante | D6: Pendiente
A7: 2 | B7: Pilotos traseros y antiniebla: encienden bien, sin humedad interior, sin fisuras | C7: Importante | D7: Pendiente
A8: 3 | B8: Intermitentes delanteros/traseros/laterales: funcionan correctamente | C8: Importante | D8: Pendiente
A9: 4 | B9: Llantas: sin golpes, deformaciones ni grietas, las 4 iguales | C9: Importante | D9: Pendiente
A10: 5 | B10: Neumaticos: profundidad de dibujo (minimo legal 1,6mm), desgaste uniforme, misma marca/modelo en las 4 | C10: Importante | D10: Pendiente
A11: 6 | B11: Neumaticos: anio de fabricacion (DOT) no excesivamente antiguo | C11: Menor | D11: Pendiente
A12: 7 | B12: Pintura: tono homogeneo panel a panel, sin diferencias de brillo (posible repintado) | C12: Critico | D12: Pendiente
A13: 8 | B13: Carroceria: holguras uniformes entre puertas, capo y maletero | C13: Critico | D13: Pendiente
A14: 9 | B14: Bajos y pasos de rueda: sin oxido excesivo ni signos de golpe/reparacion | C14: Critico | D14: Pendiente
A15: 10 | B15: Parabrisas y cristales: sin grietas ni impactos grandes, marcado de fabrica coherente en todos | C15: Importante | D15: Pendiente
A16: 11 | B16: Retrovisores: electricos, plegado, calefactables si aplica, sin grietas | C16: Menor | D16: Pendiente
A17: 12 | B17: Parachoques delantero/trasero: sin fisuras, bien anclados, tornilleria sin marcas de haber sido desmontada | C17: Critico | D17: Pendiente
... A21: 16 | B21: Consultar historial de siniestros/kilometraje en un portal tipo Car-Pass/HPI/Carfax si esta disponible para el pais de origen | C21: Importante | D21: Pendiente
B22: MECANICA
A23: 17 | B23: Nivel y aspecto del aceite de motor (ni muy oscuro ni con aspecto lechoso) | C23: Critico | D23: Pendiente
A24: 18 | B24: Fugas de aceite en el motor, carter o juntas | C24: Critico | D24: Pendiente
A25: 19 | B25: Nivel y color del liquido refrigerante, sin fugas en radiador o manguitos | C25: Critico | D25: Pendiente
A26: 20 | B26: Liquido de frenos: nivel correcto, sin aspecto turbio | C26: Critico | D26: Pendiente
A27: 21 | B27: Liquido de direccion/servo: nivel correcto | C27: Importante | D27: Pendiente
A28: 22 | B28: Correa/cadena de distribucion: constatar si esta cambiada segun el historico del fabricante | C28: Critico | D28: Pendiente
A29: 23 | B29: Bateria: estado, fecha de fabricacion, bornes sin sulfatacion | C29: Importante | D29: Pendiente
A30: 24 | B30: Arranque en frio: sin humo azul (aceite) ni blanco persistente (junta culata) | C30: Critico | D30: Pendiente
A31: 25 | B31: Ruidos de motor al ralenti: sin golpeteos ni silbidos anomalos | C31: Critico | D31: Pendiente
A32: 26 | B32: Caja de cambios (manual/automatica/DSG): cambios suaves, sin tirones, sin retardo al meter marcha | C32: Critico | D32: Pendiente
A33: 27 | B33: Embrague/convertidor: sin patinazos ni vibraciones al acelerar | C33: Critico | D33: Pendiente
A34: 28 | B34: Suspension: sin ruidos al pasar baches, amortiguadores sin fugas de aceite | C34: Critico | D34: Pendiente
... A39: 33 | B39: Soportes de motor (silentblocks): sin holguras ni ruidos al acelerar/frenar en punto muerto | C39: Importante | D39: Pendiente
B40: INTERIOR
A41: 34 | B41: Asientos: tapiceria sin roturas ni manchas, ajustes electricos/manuales funcionan | C41: Menor | D41: Pendiente
A42: 35 | B42: Volante: sin desgaste excesivo (indicativo de kilometraje real), botones multifuncion operativos | C42: Menor | D42: Pendiente
A43: 36 | B43: Salpicadero: todos los testigos se apagan tras el arranque, sin luces de averia encendidas | C43: Critico | D43: Pendiente
A44: 37 | B44: Climatizador: frio y calor en ambas zonas, sin olores raros al encender | C44: Importante | D44: Pendiente
A45: 38 | B45: Sistema multimedia / radio / pantalla tactil: touch responde bien, Bluetooth y conectividad movil funcionan | C45: Menor | D45: Pendiente
A46: 39 | B46: Cuadro digital / multifuncion: sin pixeles muertos ni parpadeos | C46: Menor | D46: Pendiente
A47: 40 | B47: Techo interior y moqueta: sin manchas de humedad (filtraciones del panoramico) | C47: Importante | D47: Pendiente
A48: 41 | B48: Cinturones de seguridad: se extienden y retraen bien, sin deshilachados, pretensores no disparados | C48: Critico | D48: Pendiente
A49: 42 | B49: Palanca/pomo de cambio: cuero en buen estado, cambios manuales (+/-) funcionan si aplica | C49: Menor | D49: Pendiente
A50: 43 | B50: Maletero: rueda de repuesto o kit de reparacion presente, suelo sin humedad | C50: Menor | D50: Pendiente
A51: 44 | B51: Ventanillas electricas: suben/bajan todas correctamente, funcion anti-atrapamiento operativa | C51: Importante | D51: Pendiente
A52: 45 | B52: Guantera con funcion de refrigeracion (si equipada): funciona | C52: Menor | D52: Pendiente
... A56: 49 | B56: Kit de emergencia: triangulos y chaleco reglamentarios presentes (si el pais de origen los exige) | C56: Menor | D56: Pendiente
B57: ELECTRONICA Y DIAGNOSIS (maquina OBD)
A58: 50 | B58: Conectar maquina de diagnosis OBD2 al puerto del vehiculo | C58: Importante | D58: Pendiente
A59: 51 | B59: Escanear TODOS los sistemas (motor, ABS, airbag, cambio, confort), no solo motor | C59: Critico | D59: Pendiente
A60: 52 | B60: Anotar codigos de error activos y codigos en memoria (pendientes/borrados recientemente) | C60: Critico | D60: Pendiente
A61: 53 | B61: Verificar si hay testigos apagados manualmente pero con fallo registrado en memoria (senial de manipulacion) | C61: Critico | D61: Pendiente
A62: 54 | B62: Leer kilometraje real desde la ECU/cuadro y contrastar con el kilometraje mostrado y el historico de servicios | C62: Critico | D62: Pendiente
A63: 55 | B63: Comprobar readiness/monitores de emisiones (relevante para la ITV de importacion) | C63: Importante | D63: Pendiente
A64: 56 | B64: Verificar funcionamiento de sensores de aparcamiento y camara trasera si equipado | C64: Menor | D64: Pendiente
A65: 57 | B65: Comprobar sistema de frenada de emergencia / asistente (test funcional si es posible) | C65: Importante | D65: Pendiente
A66: 58 | B66: Verificar campanias de recall pendientes o actualizaciones de software con el VIN en la web del fabricante | C66: Importante | D66: Pendiente
A67: 59 | B67: Guardar/foto del informe de diagnosis como respaldo documental de la compra | C67: Importante | D67: Pendiente
B68: PRUEBA DE CARRETERA
A69: 60 | B69: Arranque en frio y ralenti estable durante 1-2 minutos antes de salir | C69: Importante | D69: Pendiente
A70: 61 | B70: Aceleracion progresiva: sin tirones, sin perdida de potencia, turbo entra con normalidad si aplica | C70: Critico | D70: Pendiente
A71: 62 | B71: Frenada en recto: el coche no se desvia, sin vibracion en el pedal ni el volante | C71: Critico | D71: Pendiente
A72: 63 | B72: Direccion centrada en recta, sin necesidad de corregir constantemente | C72: Critico | D72: Pendiente
A73: 64 | B73: Cambios en modo automatico y manual (+/-): rapidez y suavidad | C73: Importante | D73: Pendiente
A74: 65 | B74: Ruidos de suspension al tomar badenes o baches a baja velocidad | C74: Importante | D74: Pendiente
A75: 66 | B75: Ruidos de rodamientos/homocineticas al girar a tope de direccion | C75: Importante | D75: Pendiente
A76: 67 | B76: Comportamiento en autovia a velocidad de crucero: vibraciones, ruido de viento excesivo | C76: Menor | D76: Pendiente
A77: 68 | B77: Test del auto-hold y freno de mano electrico si equipado | C77: Menor | D77: Pendiente
A78: 69 | B78: Frenada de emergencia a baja velocidad en zona segura: ABS/ESP activan correctamente | C78: Critico | D78: Pendiente
B79: NEGOCIACION Y CIERRE
A80: 70 | B80: Vehiculo declarado libre de accidentes ("Unfallfrei" o equivalente) de forma explicita y por escrito | C80: Critico | D80: Pendiente
A81: 71 | B81: Contrato de compraventa revisado y traducido antes de firmar | C81: Critico | D81: Pendiente
A82: 72 | B82: Descuento negociado sobre el precio de partida (ver pestania 'Plantillas de mensaje') | C82: Importante | D82: Pendiente
A83: 73 | B83: Limite de transferencia bancaria ampliado si se paga por transferencia instantanea | C83: Importante | D83: Pendiente
A84: 74 | B84: Tipo de interes del prestamo negociado en oficina, no solo por la app (si aplica financiacion) | C84: Importante | D84: Pendiente
A85: 75 | B85: Plan B de vendedor/concesionario alternativo localizado por si la operacion no se cierra | C85: Menor | D85: Pendiente
A86: 76 | B86: Derecho de desistimiento del prestamo verificado: plazo legal (normalmente 14 dias naturales en la UE) | C86: Importante | D86: Pendiente
A88: Resumen
B89: Puntos OK | C89: =COUNTIF(C5:C86,"OK")
B90: Puntos a revisar | C90: =COUNTIF(C5:C86,"Revisar")
B91: Puntos pendientes | C91: =COUNTIF(C5:C86,"Pendiente")
B92: Total puntos revisados | C92: =76
A94: Estado: escribe OK / Revisar / Pendiente / No aplica en la columna Estado. Prioridad Critico = hallazgo potencialmente bloqueante para la compra.

Sheet Checklist documentacion
A1: Checklist de documentacion para importar
A2: Documentos a solicitar/reunir antes y durante la compra, y pasos legales tras la llegada a Espania.
A4: DOCUMENTOS A REUNIR
A5: # | B5: Documento | C5: Recibido | D5: Notas
A6: 1 | B6: Zulassungsbescheinigung Teil I (permiso de circulacion) o equivalente del pais de origen | C6: No
A7: 2 | B7: Zulassungsbescheinigung Teil II (ficha tecnica / tarjeta del vehiculo) o equivalente | C7: No
A8: 3 | B8: COC - Certificate of Conformity | C8: No
A9: 4 | B9: Ultimo informe de ITV/inspeccion tecnica del pais de origen (ej. TUV/HU en Alemania) | C9: No
A10: 5 | B10: VIN (numero de bastidor) verificado | C10: No
A11: 6 | B11: Historial de mantenimiento (digital o libro sellado) | C11: No
A12: 7 | B12: Contrato de compraventa revisado y traducido | C12: No
A13: 8 | B13: Factura de compra | C13: No
A14: 9 | B14: Declaracion de libre de accidentes (por escrito) | C14: No
A15: 10 | B15: Placas temporales / matricula de transito + seguro temporal | C15: No
A16: 11 | B16: Justificante de pago (transferencia) | C16: No
A17: 12 | B17: Solicitud de ITV espaniola de importacion | C17: No
... A20: 15 | B20: Poliza de seguro espaniola activa antes de circular con matricula definitiva | C20: No
A22: PASOS TRAS LA LLEGADA A ESPANIA (PLAZOS LEGALES)
A23: Plazo legal general: 30 dias naturales desde la entrada en Espania para completar homologacion e impuestos. Confirmar plazo vigente con gestoria.
A24: # | B24: Paso | C24: Plazo orientativo | D24: Hecho | E24: Notas
A25: 1 | B25: Solicitar cita para ITV de vehiculos importados | C25: Cuanto antes tras llegar | D25: No
A26: 2 | B26: Pasar la ITV de importacion | C26: Dentro de los 30 dias | D26: No
A27: 3 | B27: Presentar Modelo 576 (autoliquidacion IEDMT) en Hacienda | C27: Dentro de los 30 dias | D27: No
A28: 4 | B28: Solicitar matriculacion definitiva en la DGT | C28: Dentro de los 30 dias | D28: No
A29: 5 | B29: Contratar seguro espaniol antes de circular con matricula definitiva | C29: Antes de retirar placas temporales | D29: No
A30: 6 | B30: Colocar placas espaniolas definitivas | C30: Tras recibir permiso de circulacion | D30: No
A31: 7 | B31: Solicitar distintivo ambiental DGT (si aplica) | C31: Tras matriculacion | D31: No
A32: 8 | B32: Dar de baja el seguro y placas temporales de origen | C32: Tras matriculacion definitiva | D32: No

Sheet Cronograma logistico
A1: Cronograma logistico de viaje (plantilla)
A2: Plantilla de viaje reutilizable: ida, protocolo financiero, cierre, contingencia, vuelta y riesgos. Adaptar tramos, duraciones y costes a cada ruta / vendedor.
A4: IDA
A5: Dia | B5: Tramo / actividad | C5: Duracion | D5: Coste (EUR) | E5: Notas
A6: Dia 1 | B6: Trayecto casa -> aeropuerto/estacion de salida | C6: ~30-45 min | D6: 6
A7: Dia 1 | B7: Vuelo/tren directo al pais de origen | C7: variable | D7: 150 | E7: Reservar con antelacion para mejor precio
A8: Dia 1 | B8: Tren/transporte local hacia la ciudad del vendedor | C8: variable | D8: 15
A9: Dia 1 | B9: Tramo final hacia el concesionario/domicilio del vendedor | C9: variable | D9: 10 | E9: Coordinar recogida con el vendedor
A11: PROTOCOLO FINANCIERO (si hay financiacion)
A12: Cuando | B12: Accion | C12: Duracion | D12: Coste (EUR) | E12: Notas
A13: Antes de viajar | B13: Gestion de financiacion en oficina bancaria (no por la app) | C13: 1h | D13: 0 | E13: Negociar tipo de interes bajo en oficina; tipo app suele ser mas alto
A14: Antes de viajar | B14: Preparar documentacion (nominas, contrato laboral, declaracion de la renta) | D14: 0 | E14: Tenerla lista en PDF por si la piden durante la gestion
A15: Antes de viajar | B15: Ampliar limite diario de transferencia si se va a pagar por transferencia instantanea | D15: 0 | E15: Confirmar limite suficiente para el importe total
A16: Antes del cierre | B16: Confirmar que el dinero esta disponible con margen antes del dia de la firma | D16: 0
A18: DIA DEL CIERRE
A19: Dia | B19: Tramo / actividad | C19: Duracion | D19: Coste (EUR) | E19: Notas
A20: Dia del cierre | B20: Inspeccion fisica + firma + pago | C20: 2-3h | D20: 0 | E20: Usar checklist de inspeccion y documentacion
A21: Dia del cierre | B21: Tramite de placas temporales + seguro temporal | C21: 1-2h | D21: 175 | E21: Verificar horario de la oficina de matriculacion
A23: VUELTA Y TRAS LA LLEGADA
A24: Dia | B24: Tramo / actividad | C24: Duracion | D24: Coste (EUR) | E24: Notas
A25: Dia de vuelta 1 | B25: Conduccion hacia Espania (tramo 1) | C25: variable | D25: 100 | E25: Repostaje + peajes
A26: Dia de vuelta 2 | B26: Conduccion hacia Espania (tramo 2 / llegada) | C26: variable | D26: 100 | E26: Repostaje + peajes
A27: Tras llegada | B27: ITV espaniola de importacion | C27: 1 dia | D27: 125
A28: Tras llegada | B28: Autoliquidacion IEDMT + matriculacion DGT | C28: 1-3 dias | D28: 55 | E28: Puede hacerse con o sin gestoria; ver checklist de documentacion
A30: TOTAL LOGISTICA | D30: =SUM(D6:D9)+SUM(D20:D21)+SUM(D25:D28)
A32: PLAN DE CONTINGENCIA
A33: Desistimiento del prestamo (si aplica): revisar plazo legal de desistimiento sin coste (en la UE suele ser 14 dias naturales desde la firma del credito). Devuelve el capital integro; puede haber intereses devengados minimos de esos dias.
A35: Plan B - portales/concesionarios alternativos (ejemplo, adaptar por pais):
A36: Portal / canal | B36: Que ofrece
A37: Portal de concesionarios seleccionados (ej. Heycar) | B37: Stock garantizado, filtrado por antiguedad y km
A38: Buscador oficial de la marca (Gebrauchtwagen del fabricante) | B38: Historial digital verificado por el fabricante
A39: Portal profesional generalista, filtro 'solo profesionales' | B39: Mayor volumen, exige filtrar por vendedor profesional
A41: REGISTRO DE RIESGOS
A42: Riesgo | B42: Probabilidad | C42: Impacto | D42: Mitigacion
A43: Golpe estructural oculto no visible en fotos | B43: Media | C43: Alto | D43: Inspeccion fisica exhaustiva + diagnosis OBD antes de firmar (ver checklist de inspeccion)
A44: El vehiculo se vende a otro comprador antes de llegar | B44: Baja | C44: Alto | D44: Confirmar disponibilidad por escrito antes de viajar
A45: Tipo de interes del prestamo alto | B45: Media | C45: Medio | D45: Negociar en oficina bancaria, no tramitar solo por la app
A46: CO2 real superior al declarado (IEDMT mayor de lo previsto) | B46: Baja | C46: Medio | D46: Confirmar CO2 exacto en el COC antes de firmar
A47: Oficina de matriculacion cerrada al llegar | B47: Media | C47: Bajo | D47: Coordinar horarios con el vendedor con antelacion
A48: Reventa mas lenta de lo esperado (nicho sin comparables directos) | B48: Media | C48: Medio | D48: Argumentario de venta preparado (ver 'Plantillas de mensaje') y margen de precio con recorrido
A49: Vicios ocultos mecanicos tras la compra | B49: Baja | C49: Alto | D49: Historial de mantenimiento completo + garantia del concesionario si la ofrece

Sheet Contactos clave
A1: Contactos clave
A2: Rellenar antes de viajar. Tenerlo tambien a mano en el movil. Ficha reutilizable para cualquier operacion.
A4: Rol | B4: Nombre / Entidad | C4: Telefono | D4: Email | E4: Notas
A5: Vendedor | B5: Martin - AlpenDrive | E5: Im Gewerbegebiet 1, 83093 Bad Endorf
A6: Gestor bancario | E6: Negociar tipo de interes en oficina
A7: Gestoria de importacion | E7: Opcional, solo si no se tramita uno mismo
A8: Seguro temporal | E8: Junto con placas provisionales
A9: Asistencia en carretera | E9: Cobertura internacional 24h, revisar poliza del seguro del coche
A10: Cita ITV importacion (Espania) | E10: Pedir cita antes de volver si es posible
A11: Traductor / apoyo idioma | E11: Si el idioma del vendedor no se domina
A12: Gestoria de venta / anuncio | E12: Si se decide vender mas adelante

Sheet Plantillas de mensaje
A1: Plantillas de mensaje (Email / WhatsApp, ES-EN-DE, profesional y distendido)
A2: Copiar y adaptar segun el vehiculo, vendedor o comprador. Tono Profesional = pensado para email; Tono Distendido = pensado para WhatsApp (ambos se pueden usar en cualquier canal). Sustituir los campos entre corchetes [ ].
A4: # | B4: Tipo de mensaje | C4: Idioma | D4: Tono | E4: Asunto (si Email) | F4: Texto
A5: COMPRA - CONTACTO Y NEGOCIACION
A6: 1 | B6: 1. Contacto inicial con el vendedor | C6: Espaniol | D6: Profesional | E6: Consulta sobre [VEHICULO] publicado en [PORTAL] | F6: Buenos dias, soy [NOMBRE] y escribo desde Espania. Estoy interesado/a en su [VEHICULO], si continua disponible y libre de accidentes. Para avanzar con el proceso de importacion a Espania, podria enviarme la documentacion del vehiculo (permiso de circulacion, ficha tecnica, Certificado de Conformidad), el VIN y el historial de mantenimiento, junto con fotos adicionales, incluyendo los bajos? Quedo a la espera de su respuesta. Un saludo, [NOMBRE].
C7: Espaniol | D7: Distendido | F7: Hola, soy [NOMBRE], desde Espania. Sigue disponible el [VEHICULO]? Me interesa para importarlo. Me puedes pasar el VIN, el historial de mantenimiento y unas fotos de los bajos? Gracias!
C8: Ingles | D8: Profesional | E8: Inquiry about the [VEHICULO] listed on [PORTAL] | F8: Good morning, my name is [NOMBRE], writing from Spain. I'm interested in your [VEHICULO], if it's still available and accident-free. To proceed with the Spanish import process, could you send me the vehicle documents (registration certificate, technical data sheet, Certificate of Conformity), the VIN, and the service history, along with a few extra photos including the underbody? Looking forward to your reply. Best regards, [NOMBRE].
C9: Ingles | D9: Distendido | F9: Hi, I'm [NOMBRE] from Spain. Is the [VEHICULO] still available? I'm looking to import it. Could you send me the VIN, service history, and a couple of underbody photos? Thanks!
C10: Aleman | D10: Profesional | E10: Anfrage zu Ihrem [VEHICULO] | F10: Guten Tag, mein Name ist [NOMBRE], ich schreibe aus Spanien. Ich interessiere mich fuer Ihren [VEHICULO], sofern er noch verfuegbar und unfallfrei ist. Fuer die Einfuhr nach Spanien benoetige ich die Fahrzeugpapiere (Zulassungsbescheinigung Teil I & II, COC), die Fahrgestellnummer (VIN) sowie die Wartungshistorie, zusaetzlich einige Fotos, auch vom Unterboden. Ich freue mich auf Ihre Antwort. Mit freundlichen Gruessen, [NOMBRE].
C11: Aleman | D11: Distendido | F11: Hallo, ich bin [NOMBRE] aus Spanien. Ist der [VEHICULO] noch zu haben? Ich moechte ihn nach Spanien importieren. Kannst du mir VIN, Wartungshistorie und ein paar Fotos vom Unterboden schicken? Danke!
A12: 2 | B12: 2. Pedir fotos / documentos adicionales | C12: Espaniol | D12: Profesional | E12: Documentacion adicional para el [VEHICULO] | F12: Gracias por la respuesta. Para completar la valoracion antes de viajar, seria posible recibir tambien el ultimo informe de inspeccion tecnica (ITV/TUV), el certificado de conformidad (COC) y un video corto del arranque en frio? Se lo agradezco de antemano.
C13: Espaniol | D13: Distendido | F13: Me puedes pasar tambien el ultimo informe de ITV/TUV y un video rapido de como arranca en frio? Asi lo tengo todo listo antes de ir. Gracias!
C14: Ingles | D14: Profesional | E14: Additional documents for the [VEHICULO] | F14: Thank you for your reply. To complete my assessment before traveling, could you also send the latest roadworthiness/inspection report, the Certificate of Conformity (COC), and a short cold-start video? I appreciate it.
C15: Ingles | D15: Distendido | F15: Could you also send the latest inspection report and a quick video of the cold start? Just want everything ready before I travel. Thanks!
C16: Aleman | D16: Profesional | E16: Weitere Unterlagen zum [VEHICULO] | F16: Vielen Dank fuer Ihre Antwort. Fuer meine Einschaetzung vor der Anreise waere es hilfreich, auch den letzten TUEV-Bericht, das COC sowie ein kurzes Video vom Kaltstart zu erhalten. Vielen Dank im Voraus.
C17: Aleman | D17: Distendido | F17: Kannst du mir noch den letzten TUEV-Bericht und ein kurzes Video vom Kaltstart schicken? Dann hab ich vor der Anreise alles parat. Danke!
A18: 3 | B18: 3. Confirmar cita para ver el coche | C18: Espaniol | D18: Profesional | E18: Confirmacion de visita - [VEHICULO] | F18: Me gustaria concretar una cita para ver el vehiculo en persona el [FECHA] sobre las [HORA]. Le confirmo que llegare con el pago listo para formalizar la compra el mismo dia si todo esta conforme. Le viene bien esa fecha?
C19: Espaniol | D19: Distendido | F19: Oye, te viene bien que vaya a verlo el [FECHA] sobre las [HORA]? Voy con el pago listo por si cerramos ese mismo dia.
C20: Ingles | D20: Profesional | E20: Visit confirmation - [VEHICULO] | F20: I would like to arrange a visit to see the vehicle in person on [FECHA] around [HORA]. I can confirm I will have payment ready to complete the purchase that same day if everything checks out. Would that date work for you?
C21: Ingles | D21: Distendido | F21: Would [FECHA] around [HORA] work for you to see the car? I'll have payment ready in case we close the deal that day.
C22: Aleman | D22: Profesional | E22: Besichtigungstermin - [VEHICULO] | F22: Ich wuerde das Fahrzeug gerne am [FECHA] gegen [HORA] persoenlich besichtigen. Bei positivem Eindruck kann ich den Kauf noch am selben Tag mit sofortiger Zahlung abschliessen. Passt Ihnen dieser Termin?
C23: Aleman | D23: Distendido | F23: Passt es dir, wenn ich am [FECHA] gegen [HORA] vorbeikomme? Ich hab die Zahlung parat, falls wir gleich abschliessen.
A24: 4 | B24: 4. Peticion de descuento | C24: Espaniol | D24: Profesional | F24: Gracias por la informacion. Estoy en disposicion de proceder con una transferencia inmediata esta misma semana, sin condiciones de financiacion ni demoras. Dado el kilometraje/historial, hay margen en el precio?
C25: Espaniol | D25: Distendido | F25: Todo perfecto, gracias! Puedo pagar por transferencia instantanea esta semana, sin lios de financiacion. Hay algo de margen en el precio?
C26: Ingles | D26: Profesional | F26: Thank you for the information. I'm ready to proceed with an immediate transfer this week - no financing conditions, no delays. Given the mileage/history, is there any flexibility on the price?
C27: Ingles | D27: Distendido | F27: All good, thanks! I can pay by instant transfer this week, no financing hassle. Any room to move on the price?
C28: Aleman | D28: Profesional | F28: Vielen Dank fuer die Informationen. Ich kann noch diese Woche eine Sofortueberweisung taetigen, ohne Finanzierung oder Verzoegerungen. Gibt es angesichts der Laufleistung/Historie noch Verhandlungsspielraum beim Preis?
C29: Aleman | D29: Distendido | F29: Danke, alles klar! Ich kann diese Woche per Sofortueberweisung zahlen, keine Finanzierung noetig. Ist beim Preis noch etwas drin?
A30: COMPRA - SEGUIMIENTO Y CIERRE
A31: 5 | B31: 5. Confirmar cierre y forma de pago | C31: Espaniol | D31: Profesional | E31: Confirmacion de compra y forma de pago - [VEHICULO] | F31: Confirmo que procederemos con la compra del [VEHICULO] por [PRECIO] EUR. El pago se realizara mediante transferencia SEPA instantanea el dia de la firma. Le agradeceria que tuviera preparado el contrato de compraventa y la documentacion indicada previamente.
C32: Espaniol | D32: Distendido | F32: Genial, cerramos entonces por [PRECIO]. Pago por transferencia instantanea el dia que firmemos. Tienes ya el contrato preparado?
C33: Ingles | D33: Profesional | E33: Purchase and payment confirmation - [VEHICULO] | F33: I confirm we will proceed with the purchase of the [VEHICULO] for EUR [PRECIO]. Payment will be made via instant bank transfer on the day of signing. I'd appreciate it if you could have the sales contract and previously requested documents ready.
C34: Ingles | D34: Distendido | F34: Great, let's go ahead at EUR [PRECIO]. I'll pay by instant transfer on signing day. Do you have the contract ready?
C35: Aleman | D35: Profesional | E35: Kaufbestaetigung und Zahlungsweise - [VEHICULO] | F35: Hiermit bestaetige ich den Kauf des [VEHICULO] zum Preis von [PRECIO] EUR. Die Zahlung erfolgt am Tag der Unterschrift per Sofortueberweisung. Ich waere dankbar, wenn Sie den Kaufvertrag und die zuvor angefragten Unterlagen bereithalten koennten.
C36: Aleman | D36: Distendido | F36: Super, dann machen wir's fuer [PRECIO] EUR fest. Zahlung per Sofortueberweisung am Tag der Unterschrift. Hast du den Vertrag schon fertig?
A37: 6 | B37: 6. Seguimiento si no responden | C37: Espaniol | D37: Profesional | E37: Seguimiento - consulta sobre [VEHICULO] | F37: Le escribi hace unos dias preguntando por el [VEHICULO] y no he tenido noticias. Sigue disponible el vehiculo? Quedo atento/a a su respuesta.
C38: Espaniol | D38: Distendido | F38: Hola de nuevo! Sigue disponible el coche? No he tenido respuesta y no quiero perder la oportunidad.
C39: Ingles | D39: Profesional | E39: Follow-up - inquiry about the [VEHICULO] | F39: I reached out a few days ago about the [VEHICULO] and haven't heard back. Is the vehicle still available? Looking forward to your reply.
C40: Ingles | D40: Distendido | F40: Hi again! Is the car still available? Haven't heard back and don't want to miss out.
C41: Aleman | D41: Profesional | E41: Nachfrage - Ihr [VEHICULO] | F41: Ich hatte vor einigen Tagen wegen des [VEHICULO] geschrieben und noch keine Rueckmeldung erhalten. Ist das Fahrzeug noch verfuegbar? Ich freue mich auf Ihre Antwort.
C42: Aleman | D42: Distendido | F42: Hallo nochmal! Ist der Wagen noch zu haben? Hab noch nichts gehoert und will die Chance nicht verpassen.
A43: 7 | B43: 7. El coche ya se vendio - pedir avisen de otros | C43: Espaniol | D43: Profesional | F43: Gracias por avisarme. Si dispone de otro vehiculo similar (mismo modelo/motorizacion o equivalente) proximamente, le agradeceria que me lo hiciera saber.
C44: Espaniol | D44: Distendido | F44: Vaya, una pena! Si te entra algo parecido avisame porfa.
C45: Ingles | D45: Profesional | F45: Thank you for letting me know. If you come across a similar vehicle (same model/engine or equivalent) in the near future, I'd appreciate it if you could let me know.
C46: Ingles | D46: Distendido | F46: Ah, too bad! If something similar comes in, please let me know.
C47: Aleman | D47: Profesional | F47: Danke fuer die Info. Falls Sie demnaechst ein aehnliches Fahrzeug (gleiches Modell/Motorisierung oder vergleichbar) bekommen, waere ich fuer eine kurze Nachricht dankbar.
C48: Aleman | D48: Distendido | F48: Schade! Falls was Aehnliches reinkommt, sag mir gerne Bescheid.
A49: 8 | B49: 8. Agradecimiento post-compra | C49: Espaniol | D49: Profesional | E49: Gracias por la operacion - [VEHICULO] | F49: Queria agradecerle de nuevo la atencion durante todo el proceso de compra del [VEHICULO]. Ha sido una experiencia muy positiva. Le deseo lo mejor y no dude en contactarme si surge algo relacionado con el vehiculo.
C50: Espaniol | D50: Distendido | F50: Muchas gracias por todo, ha sido un placer! Cualquier cosa me dices.
C51: Ingles | D51: Profesional | E51: Thank you - [VEHICULO] purchase | F51: I wanted to thank you again for your help throughout the purchase of the [VEHICULO]. It was a great experience. All the best, and please don't hesitate to reach out if anything comes up.
C52: Ingles | D52: Distendido | F52: Thanks so much for everything, it was a pleasure! Let me know if anything comes up.
C53: Aleman | D53: Profesional | E53: Vielen Dank - Kauf [VEHICULO] | F53: Ich moechte mich nochmals fuer die Unterstuetzung waehrend des gesamten Kaufprozesses des [VEHICULO] bedanken. Es war eine sehr positive Erfahrung. Alles Gute, und melden Sie sich gerne, falls etwas ist.
C54: Aleman | D54: Distendido | F54: Danke fuer alles, hat echt Spass gemacht! Meld dich, falls was ist.
A55: CLIENTE - PRESENTAR Y CERRAR LA OPERACION
A56: 9 | B56: 9. Presentar el coche a un cliente interesado | C56: Espaniol | D56: Profesional | E56: Informacion sobre el [VEHICULO] para tu importacion | F56: Gracias por tu interes. Este [VEHICULO] esta disponible para gestionar su importacion a tu nombre. Con [KM] km e historial de mantenimiento verificado, la documentacion de importacion queda completa y en regla desde el primer momento. Quedo a tu disposicion para resolver cualquier duda o concretar una visita.
C57: Espaniol | D57: Distendido | F57: Hola! Si, sigue disponible para importartelo. Es un [VEHICULO] con historial completo, y te lo dejo con toda la documentacion de importacion en regla desde el minuto uno. Quieres que quedemos para verlo?
C58: Ingles | D58: Profesional | E58: Information about the [VEHICULO] for your import | F58: Thank you for your interest. This [VEHICULO] is available for me to manage its import in your name. With [KM] km and a verified service history, the import documentation will be complete and in order from day one. I'm happy to answer any questions or arrange a viewing.
C59: Ingles | D59: Distendido | F59: Hi! Yes, it's still available for me to import for you. It's a [VEHICULO] with full service history, and I'll hand it over with all the import paperwork in order from day one. Want to arrange a time to see it?
C60: Aleman | D60: Profesional | E60: Informationen zum [VEHICULO] fuer Ihre Einfuhr | F60: Vielen Dank fuer Ihr Interesse. Dieser [VEHICULO] steht zur Verfuegung, damit ich die Einfuhr auf Ihren Namen abwickle. Mit [KM] km und nachweislich gepflegter Wartungshistorie ist die Einfuhrdokumentation von Anfang an vollstaendig und in Ordnung. Gerne beantworte ich weitere Fragen oder vereinbare einen Besichtigungstermin.
C61: Aleman | D61: Distendido | F61: Hallo! Ja, ich kann ihn fuer Sie einfuehren. Ein [VEHICULO] mit komplettem Serviceheft, und Sie bekommen ihn mit allen Einfuhrpapieren von Anfang an in Ordnung. Lust auf einen Besichtigungstermin?
A62: 10 | B62: 10. Negociar honorarios/precio con el cliente | C62: Espaniol | D62: Profesional | F62: Entiendo tu interes en ajustar el precio. El importe todo incluido ya refleja el estado del vehiculo, los costes de importacion y mis honorarios de gestion. Puedo ofrecerte un pequenio ajuste de [AJUSTE] EUR si confirmas esta semana.
C63: Espaniol | D63: Distendido | F63: Te entiendo, pero el precio todo incluido ya esta ajustado con lo que cuesta traerlo legal y en regla, mas mis honorarios. Si confirmamos esta semana, te puedo hacer algo de hueco.
C64: Ingles | D64: Profesional | F64: I understand you'd like some flexibility on the price. The all-inclusive price already reflects the vehicle's condition, the import costs, and my service fee. I can offer a small adjustment of EUR [AJUSTE] if you confirm this week.
C65: Ingles | D65: Distendido | F65: I get it, but the all-inclusive price already accounts for everything it takes to import it properly, plus my fee. If we confirm this week I can knock a bit off.
C66: Aleman | D66: Profesional | F66: Ich verstehe Ihr Interesse an einem besseren Preis. Der Gesamtpreis beruecksichtigt bereits den Zustand des Fahrzeugs, die Einfuhrkosten und mein Servicehonorar. Bei einer Bestaetigung diese Woche kann ich Ihnen [AJUSTE] EUR entgegenkommen.
C67: Aleman | D67: Distendido | F67: Kann ich verstehen, aber der Gesamtpreis ist schon fair kalkuliert mit allem, was die Einfuhr kostet, plus meinem Honorar. Wenn wir diese Woche bestaetigen, geht noch etwas.
A68: 11 | B68: 11. Confirmar visita con el cliente | C68: Espaniol | D68: Profesional | E68: Confirmacion de visita - [VEHICULO] | F68: Perfecto, te espero el [FECHA] a las [HORA] en [LUGAR] para ver el vehiculo. Si necesitas indicaciones o tienes alguna pregunta antes de la visita, quedo a tu disposicion.
C69: Espaniol | D69: Distendido | F69: Vale, te espero el [FECHA] a las [HORA] en [LUGAR]. Cualquier cosa me avisas!
C70: Ingles | D70: Profesional | E70: Visit confirmation - [VEHICULO] | F70: Perfect, I'll expect you on [FECHA] at [HORA] at [LUGAR] to see the vehicle. If you need directions or have any questions beforehand, feel free to reach out.
C71: Ingles | D71: Distendido | F71: Cool, see you on [FECHA] at [HORA] at [LUGAR]. Let me know if anything changes!
C72: Aleman | D72: Profesional | E72: Terminbestaetigung - [VEHICULO] | F72: Sehr gerne, ich erwarte Sie am [FECHA] um [HORA] in [LUGAR] zur Besichtigung. Bei Fragen oder falls Sie eine Wegbeschreibung benoetigen, melden Sie sich gerne.
C73: Aleman | D73: Distendido | F73: Alles klar, bis [FECHA] um [HORA] in [LUGAR]. Sag Bescheid, falls sich was aendert!
A74: 12 | B74: 12. Cerrar la operacion de importacion con el cliente | C74: Espaniol | D74: Profesional | E74: Inicio de la gestion de importacion - [VEHICULO] | F74: Confirmo el inicio de la gestion de importacion del [VEHICULO] por [PRECIO] EUR todo incluido (coche, importacion y honorarios). Matriculare el vehiculo a tu nombre y te facilitare toda la documentacion, incluida la de importacion, y el contrato de servicio para formalizarlo. Gracias por tu confianza.
C75: Espaniol | D75: Distendido | F75: Genial, arrancamos con la importacion por [PRECIO] (todo incluido)! Te paso toda la documentacion y el contrato de servicio para firmarlo. Gracias por la confianza!
C76: Ingles | D76: Profesional | E76: Import service start - [VEHICULO] | F76: I confirm we'll start managing the import of the [VEHICULO] for EUR [PRECIO] all-inclusive (car, import, and service fee). The vehicle will be registered in your name, and I'll provide all documentation, including import papers, and the service agreement to finalize it. Thank you for your trust.
C77: Ingles | D77: Distendido | F77: Awesome, let's get the import started for EUR [PRECIO] (all-in)! I'll send over all the paperwork and the service agreement to sign. Thanks for trusting me with this!
C78: Aleman | D78: Profesional | E78: Beginn der Einfuhrabwicklung - [VEHICULO] | F78: Hiermit bestaetige ich den Beginn der Einfuhrabwicklung fuer den [VEHICULO] zum Gesamtpreis von [PRECIO] EUR (Fahrzeug, Einfuhr und Servicehonorar). Das Fahrzeug wird auf Ihren Namen zugelassen. Ich stelle Ihnen alle Unterlagen, inklusive Einfuhrdokumente, sowie den Servicevertrag zur Verfuegung. Vielen Dank fuer Ihr Vertrauen.
C79: Aleman | D79: Distendido | F79: Super, dann starten wir die Einfuhr fuer [PRECIO] EUR (Gesamtpreis)! Ich schicke Ihnen alle Unterlagen und den Servicevertrag zum Unterschreiben. Danke fuers Vertrauen!

Sheet Anuncio de venta
A1: Anuncio de venta
A2: Texto listo para publicar, generado a partir de los datos del vehiculo y la investigacion. Revisar antes de publicar y adaptar fotos.
A4: TITULO Y PRECIO
B5: Titulo del anuncio
B6: Precio todo incluido (publicado) | C6: =('Vehiculo y resumen'!B45)
A8: DESCRIPCION CORTA (RRSS - Instagram / Facebook / grupos)
B9: Texto corto
A12: DESCRIPCION LARGA (portal de venta - Wallapop / Coches.net / AutoScout24)
B13: Texto largo
A16: FICHA TECNICA RESUMIDA (para el cuerpo del anuncio)
B17: Marca y modelo | C17: =IF('Vehiculo y resumen'!B6="","",'Vehiculo y resumen'!B6)
B18: Motorizacion | C18: =IF('Vehiculo y resumen'!B7="","",'Vehiculo y resumen'!B7)
B19: Combustible | C19: =IF('Vehiculo y resumen'!B8="","",'Vehiculo y resumen'!B8)
B20: Cambio | C20: =IF('Vehiculo y resumen'!B9="","",'Vehiculo y resumen'!B9)
B21: Anio | C21: =IF('Vehiculo y resumen'!B12="","",'Vehiculo y resumen'!B12)
B22: Kilometraje | C22: =IF('Vehiculo y resumen'!B13="","",'Vehiculo y resumen'!B13)
B23: Color | C23: =IF('Vehiculo y resumen'!B15="","",'Vehiculo y resumen'!B15)
B24: Equipamiento destacado | C24: =IF('Vehiculo y resumen'!B17="","",'Vehiculo y resumen'!B17)
A26: HASHTAGS / PALABRAS CLAVE (para RRSS)
A29: FOTOS RECOMENDADAS ANTES DE PUBLICAR
B30: Frontal 3/4 (exterior, luz de dia)
B31: Trasera 3/4
B32: Lateral completo (ambos lados si hay marcas)
B33: Interior: salpicadero y volante
B34: Interior: asientos delanteros y traseros
B35: Maletero
B36: Cuentakilometros (odometro visible)
B37: Motor (capo abierto)
B38: Bajos del vehiculo (si es posible)
B39: Neumaticos (profundidad de dibujo)
B40: Cualquier dano o desperfecto visible (transparencia)
